virtuoso_utilities/bulk_load.py
virtuoso_utilities/dump_quadstore.py
virtuoso_utilities/isql_helpers.py
virtuoso_utilities/launch_virtuoso.py
virtuoso_utilities/native_entrypoint.py
virtuoso_utilities/rebuild_fulltext_index.py
virtuoso_utilities-1.10.0.dist-info/METADATA
virtuoso_utilities-1.10.0.dist-info/WHEEL
virtuoso_utilities-1.10.0.dist-info/entry_points.txt
virtuoso_utilities-1.10.0.dist-info/licenses/LICENSE
virtuoso_utilities-1.10.0.dist-info/RECORD
