Metadata-Version: 2.4
Name: virtuoso-utilities
Version: 1.10.0
Summary: A collection of Python utilities for interacting with OpenLink Virtuoso.
Author-email: arcangelo7 <arcangelo.massari@unibo.it>
License: ISC
License-File: LICENSE
Requires-Python: >=3.9
Requires-Dist: psutil<8.0.0,>=7.0.0
Requires-Dist: tqdm<5.0.0,>=4.67.1
